nbdocgen/__init__.py
nbdocgen/docgen.py
nbdocgen-0.1.0.dist-info/LICENSE
nbdocgen-0.1.0.dist-info/METADATA
nbdocgen-0.1.0.dist-info/WHEEL
nbdocgen-0.1.0.dist-info/entry_points.txt
nbdocgen-0.1.0.dist-info/RECORD
