Metadata-Version: 2.1
Name: nbdocgen
Version: 0.1.0
Summary: nbdocgen is a command line tool to generate documentation for each and every cell in a Jupyter notebook using OpenAI Chat Completion APIs.
License: MIT
Author: Santi Adavani
Author-email: santis@gmail.com
Requires-Python: >=3.8,<4.0
Classifier: License :: OSI Approved :: MIT License
Classifier: Programming Language :: Python :: 3
Classifier: Programming Language :: Python :: 3.8
Classifier: Programming Language :: Python :: 3.9
Classifier: Programming Language :: Python :: 3.10
Classifier: Programming Language :: Python :: 3.11
Requires-Dist: black (>=23.7.0,<24.0.0)
Requires-Dist: click (>=8.1.6,<9.0.0)
Requires-Dist: openai (>=0.27.8,<0.28.0)
Requires-Dist: rich (>=13.4.2,<14.0.0)
